vk_exchange_rates
