Metadata-Version: 2.1
Name: vk-exchange-rates
Version: 0.0.3
Summary: A small library for getting information on cash exchange rates of PrivatBank and the NBU on the selected date range
Home-page: UNKNOWN
Author: Vitold Kliain
Author-email: kliain.tech@gmail.com
License: MIT
Project-URL: Source, https://gtlb.jetsoftpro.com/vitoldkliain/vk-exchange-rates
Keywords: python,exchange rate,privatbank,nbu,graph,diagram
Platform: UNKNOWN
Classifier: Intended Audience :: Education
Classifier: Programming Language :: Python :: 3
Classifier: License :: OSI Approved :: MIT License
Classifier: Operating System :: OS Independent
